autocml/__init__.py
autocml/argparse.py
autocml/auth.py
autocml/connections.py
autocml/parallel.py
autocml/bin/__init__.py
autocml/bin/add_users.py
autocml/bin/bulk_lab.py
autocml/bin/dump_cfgs.py
autocml/bin/dump_cmds.py
autocml/bin/dump_pings.py
autocml/bin/pcap.py
autocml/bin/start_session.py
autocml/bin/verify_ints.py
autocml-0.0.5.dist-info/METADATA
autocml-0.0.5.dist-info/WHEEL
autocml-0.0.5.dist-info/entry_points.txt
autocml-0.0.5.dist-info/top_level.txt
autocml-0.0.5.dist-info/RECORD
