Metadata-Version: 2.1
Name: autocml
Version: 0.0.5
Summary: A set of wrapper libraries and command line tools for interacting with Cisco's CML or VIRL2 application
Home-page: https://github.com/chrismooredev/autocml-py
Author: Chris Moore
Author-email: dev@chrismoore.dev
License: UNKNOWN
Project-URL: Bug Reports, https://github.com/chrismooredev/autocml-py/issues
Project-URL: Source, https://github.com/chrismooredev/autocml-py/
Keywords: sample,setuptools,development
Platform: UNKNOWN
Classifier: Development Status :: 3 - Alpha
Classifier: Intended Audience :: Developers
Classifier: Topic :: Software Development :: Build Tools
Classifier: License :: OSI Approved :: MIT License
Classifier: Programming Language :: Python :: 3
Classifier: Programming Language :: Python :: 3.6
Classifier: Programming Language :: Python :: 3.7
Classifier: Programming Language :: Python :: 3.8
Classifier: Programming Language :: Python :: 3.9
Classifier: Programming Language :: Python :: 3 :: Only
Requires-Python: >=3.7, <4
Requires-Dist: pyyaml
Requires-Dist: netmiko
Requires-Dist: ntc-templates
Requires-Dist: virl2-client
